statshub/__init__.py
statshub/prob/__init__.py
statshub/prob/functions.py
statshub-0.0.5.dist-info/LICENSE.txt
statshub-0.0.5.dist-info/METADATA
statshub-0.0.5.dist-info/WHEEL
statshub-0.0.5.dist-info/top_level.txt
statshub-0.0.5.dist-info/RECORD
