Metadata-Version: 2.1
Name: statshub
Version: 0.0.5
Summary: Python Library to perform various Mathematical and Statical Operations.
Author: Savi
License: MIT
License-File: LICENSE.txt
